bytex/__init__.py
bytex/annotations.py
bytex/endianness.py
bytex/errors.py
bytex/field.py
bytex/py.typed
bytex/sign.py
bytex/types.py
bytex/bits/__init__.py
bytex/bits/bit_buffer.py
bytex/bits/types.py
bytex/bits/utils.py
bytex/codecs/__init__.py
bytex/codecs/base_codec.py
bytex/codecs/base_list_codec.py
bytex/codecs/enum_codec.py
bytex/codecs/basic/__init__.py
bytex/codecs/basic/char_codec.py
bytex/codecs/basic/data_codec.py
bytex/codecs/basic/flag_codec.py
bytex/codecs/basic/integer_codec.py
bytex/codecs/basic/structure_codec.py
bytex/codecs/exact/__init__.py
bytex/codecs/exact/exact_bytes_codec.py
bytex/codecs/exact/exact_list_codec.py
bytex/codecs/exact/exact_string_codec.py
bytex/codecs/fixed/__init__.py
bytex/codecs/fixed/fixed_bytes_codec.py
bytex/codecs/fixed/fixed_integers_codec.py
bytex/codecs/fixed/fixed_string_codec.py
bytex/codecs/prefix/__init__.py
bytex/codecs/prefix/prefix_bytes_codec.py
bytex/codecs/prefix/prefix_list_codec.py
bytex/codecs/prefix/prefix_string_codec.py
bytex/codecs/terminated/__init__.py
bytex/codecs/terminated/terminated_bytes_codec.py
bytex/codecs/terminated/terminated_list_codec.py
bytex/codecs/terminated/terminated_string_codec.py
bytex/length_encodings/__init__.py
bytex/length_encodings/base_length_encoding.py
bytex/length_encodings/exact.py
bytex/length_encodings/fixed.py
bytex/length_encodings/prefix.py
bytex/length_encodings/terminator.py
bytex/structure/__init__.py
bytex/structure/_structure.py
bytex/structure/structure.py
bytex/structure/structure_meta.py
bytex/structure/types.py
bytex/structure/methods/__init__.py
bytex/structure/methods/dump.py
bytex/structure/methods/dump_bits.py
bytex/structure/methods/init.py
bytex/structure/methods/parse.py
bytex/structure/methods/parse_bits.py
bytex/structure/methods/repr.py
bytex/structure/methods/validate.py
bytex/structure_enum/__init__.py
bytex/structure_enum/_structure_enum.py
bytex/structure_enum/structure_enum.py
bytex-0.2.0.dist-info/licenses/LICENSE
bytex-0.2.0.dist-info/METADATA
bytex-0.2.0.dist-info/WHEEL
bytex-0.2.0.dist-info/top_level.txt
bytex-0.2.0.dist-info/RECORD
