Metadata-Version: 2.4
Name: bytex
Version: 0.2.0
Summary: Pydantic-like binary validation
License: MIT
Requires-Python: >=3.8
License-File: LICENSE
Provides-Extra: test
Requires-Dist: pytest==8.3.5; extra == "test"
Requires-Dist: mypy==1.17.1; extra == "test"
Requires-Dist: black==25.1.0; extra == "test"
Requires-Dist: ruff==0.12.10; extra == "test"
Provides-Extra: examples
Requires-Dist: scapy==2.6.1; extra == "examples"
Dynamic: license-file
